alibabacloud_domain20180208/__init__.py
alibabacloud_domain20180208/client.py
alibabacloud_domain20180208/models/__init__.py
alibabacloud_domain20180208/models/_accept_demand_request.py
alibabacloud_domain20180208/models/_accept_demand_response.py
alibabacloud_domain20180208/models/_accept_demand_response_body.py
alibabacloud_domain20180208/models/_batch_intrude_domains_request.py
alibabacloud_domain20180208/models/_batch_intrude_domains_response.py
alibabacloud_domain20180208/models/_batch_intrude_domains_response_body.py
alibabacloud_domain20180208/models/_batch_intrude_domains_shrink_request.py
alibabacloud_domain20180208/models/_batch_query_push_status_request.py
alibabacloud_domain20180208/models/_batch_query_push_status_response.py
alibabacloud_domain20180208/models/_batch_query_push_status_response_body.py
alibabacloud_domain20180208/models/_batch_query_push_status_shrink_request.py
alibabacloud_domain20180208/models/_batch_recall_push_request.py
alibabacloud_domain20180208/models/_batch_recall_push_response.py
alibabacloud_domain20180208/models/_batch_recall_push_response_body.py
alibabacloud_domain20180208/models/_batch_recall_push_shrink_request.py
alibabacloud_domain20180208/models/_bid_domain_request.py
alibabacloud_domain20180208/models/_bid_domain_response.py
alibabacloud_domain20180208/models/_bid_domain_response_body.py
alibabacloud_domain20180208/models/_change_auction_request.py
alibabacloud_domain20180208/models/_change_auction_response.py
alibabacloud_domain20180208/models/_change_auction_response_body.py
alibabacloud_domain20180208/models/_check_domain_status_request.py
alibabacloud_domain20180208/models/_check_domain_status_response.py
alibabacloud_domain20180208/models/_check_domain_status_response_body.py
alibabacloud_domain20180208/models/_check_push_receiver_request.py
alibabacloud_domain20180208/models/_check_push_receiver_response.py
alibabacloud_domain20180208/models/_check_push_receiver_response_body.py
alibabacloud_domain20180208-1.8.1.dist-info/LICENSE
alibabacloud_domain20180208-1.8.1.dist-info/METADATA
alibabacloud_domain20180208-1.8.1.dist-info/WHEEL
alibabacloud_domain20180208-1.8.1.dist-info/top_level.txt
alibabacloud_domain20180208-1.8.1.dist-info/RECORD
